[
  {
    "path": "posts/2019-11-18-article-3/",
    "title": "Article 3 : US national-scale study shows that invasive grasses promote wildfire",
    "description": "This article is talking about the fact that invasives grasses can change so much their environnement that they can increase fire occurence.",
    "author": [
      {
        "name": "Rodrigue Tesse",
        "url": {}
      }
    ],
    "date": "2019-11-18",
    "categories": [
      "Invasive species",
      "Grasses",
      "Wild fires"
    ],
    "preview": "posts/2019-11-18-article-3/image/1024px-Fire_in_Ranua.JPG",
    "last_modified": "2019-11-19T18:10:28+01:00"
  },
  {
    "path": "posts/2019-11-12-article-2/",
    "title": "Article 2 : Invasive carp fueled by mussel poop spread across Lake Michigan",
    "description": "Analysis of an article that explaining how much the introducing of Asian carps could destroy the local ecosystem.",
    "author": [
      {
        "name": "Rodrigue Tesse",
        "url": {}
      }
    ],
    "date": "2019-11-12",
    "categories": [
      "Invasive species",
      "Fishes"
    ],
    "preview": "posts/2019-11-12-article-2/image/080919_cw_carp_feat-1028x579.jpg",
    "last_modified": "2019-11-18T18:03:48+01:00"
  },
  {
    "path": "posts/2019-11-12-my-english-activity-log/",
    "title": "My english activity log",
    "description": "A short description of the post.",
    "author": [
      {
        "name": "Rodrigue Tesse",
        "url": {}
      }
    ],
    "date": "2019-11-10",
    "categories": [],
    "preview": {},
    "last_modified": "2019-11-17T09:59:25+01:00"
  },
  {
    "path": "posts/2019-09-18-article-1/",
    "title": "Article 1 : Look out, invasive species: The robots are coming",
    "description": "Analysis about the using of robots in the fight against the invasive species.",
    "author": [
      {
        "name": "Rodrigue Tesse",
        "url": {}
      }
    ],
    "date": "2019-10-20",
    "categories": [
      "Invasive species",
      "Fishes"
    ],
    "preview": "posts/2019-09-18-article-1/image/800px-Gambusia_affinis_male.jpg",
    "last_modified": "2019-11-17T09:58:11+01:00"
  }
]
